google_cloud_hsm/__init__.py
google_cloud_hsm/__version__.py
google_cloud_hsm/config.py
google_cloud_hsm/exceptions.py
google_cloud_hsm/utils.py
google_cloud_hsm/accounts/__init__.py
google_cloud_hsm/accounts/gcp_kms_account.py
google_cloud_hsm/types/__init__.py
google_cloud_hsm/types/ethereum_types.py
google_cloud_hsm-0.0.1.dist-info/METADATA
google_cloud_hsm-0.0.1.dist-info/WHEEL
google_cloud_hsm-0.0.1.dist-info/licenses/AUTHORS.md
google_cloud_hsm-0.0.1.dist-info/licenses/LICENSE
google_cloud_hsm-0.0.1.dist-info/RECORD
