Metadata-Version: 2.4
Name: google-cloud-hsm
Version: 0.0.1
Summary: Cloud HSM to sign Web3.py Ethereum transactions
Project-URL: Documentation, https://Aviksaikat.github.io/google-cloud-hsm/
Project-URL: Source, https://github.com/Ankvik-Tech-Labs/google-cloud-hsm
Author-email: google-cloud-hsm <github.maturity983@passinbox.com>
License: 
License-File: AUTHORS.md
License-File: LICENSE
Classifier: Programming Language :: Python :: 3
Classifier: Programming Language :: Python :: 3.10
Classifier: Programming Language :: Python :: Implementation :: CPython
Classifier: Programming Language :: Python :: Implementation :: PyPy
Requires-Python: >=3.10
Provides-Extra: dev
Requires-Dist: ipython; extra == 'dev'
Requires-Dist: web3; extra == 'dev'
